pysummarization/__init__.py
pysummarization/abstractable_doc.py
pysummarization/abstractable_semantics.py
pysummarization/clusterable_doc.py
pysummarization/computable_distance.py
pysummarization/n_gram.py
pysummarization/nlp_base.py
pysummarization/readable_web_pdf.py
pysummarization/similarity_filter.py
pysummarization/tokenizable_doc.py
pysummarization/vectorizable_sentence.py
pysummarization/vectorizable_token.py
pysummarization/web_scraping.py
pysummarization/abstractabledoc/__init__.py
pysummarization/abstractabledoc/std_abstractor.py
pysummarization/abstractabledoc/top_n_rank_abstractor.py
pysummarization/abstractablesemantics/__init__.py
pysummarization/abstractablesemantics/enc_dec_ad.py
pysummarization/abstractablesemantics/re_seq_2_seq.py
pysummarization/abstractablesemantics/_mxnet/__init__.py
pysummarization/abstractablesemantics/_mxnet/enc_dec_ad.py
pysummarization/abstractablesemantics/_mxnet/re_seq_2_seq.py
pysummarization/clusterabledoc/__init__.py
pysummarization/clusterabledoc/k_means.py
pysummarization/computabledistance/__init__.py
pysummarization/computabledistance/euclid_distance.py
pysummarization/computabledistance/kl_divergence.py
pysummarization/computabledistance/kldivergence/__init__.py
pysummarization/computabledistance/kldivergence/js_divergence.py
pysummarization/iteratabledata/__init__.py
pysummarization/iteratabledata/token_iterator.py
pysummarization/iteratabledata/_mxnet/__init__.py
pysummarization/iteratabledata/_mxnet/token_iterator.py
pysummarization/nlpbase/__init__.py
pysummarization/nlpbase/auto_abstractor.py
pysummarization/nlpbase/autoabstractor/__init__.py
pysummarization/nlpbase/autoabstractor/n_gram_auto_abstractor.py
pysummarization/readablewebpdf/__init__.py
pysummarization/readablewebpdf/web_pdf_reading.py
pysummarization/similarityfilter/__init__.py
pysummarization/similarityfilter/dice.py
pysummarization/similarityfilter/encoder_decoder_clustering.py
pysummarization-1.1.5.dist-info/METADATA
pysummarization-1.1.5.dist-info/RECORD
pysummarization-1.1.5.dist-info/WHEEL
pysummarization-1.1.5.dist-info/top_level.txt
