Metadata-Version: 2.1
Name: pysummarization
Version: 1.1.5
Summary: pysummarization is Python library for the automatic summarization, document abstraction, and text filtering in relation to Encoder/Decoder based on LSTM and LSTM-RTRBM.
Home-page: https://github.com/accel-brain/accel-brain-code/tree/master/Automatic-Summarization/
Author: accel-brain
Author-email: info@accel-brain.co.jp
License: GPL2
Keywords: Automatic summarization document abstraction abstract text filtering
Platform: UNKNOWN
Classifier: Development Status :: 5 - Production/Stable
Classifier: Intended Audience :: Information Technology
Classifier: Intended Audience :: Science/Research
Classifier: Topic :: Text Processing
Classifier: Topic :: Scientific/Engineering :: Artificial Intelligence
Classifier: License :: OSI Approved :: GNU General Public License v2 (GPLv2)
Classifier: Programming Language :: Python :: 3
Requires-Dist: numpy
Requires-Dist: nltk
